{
  "schemaVersion": "2.0",
  "domainId": "local-on-demand-delivery-marketplace",
  "domainName": "Local On-Demand Delivery Marketplace",
  "timeframe": "next_quarter",
  "generatedOn": "2026-04-22",
  "discoveries": [
    {
      "id": "discovery-grocery-substitution-trust",
      "title": "Grocery substitution trust discovery",
      "description": "Determine which substitution preferences, shopper communication, and item availability signals improve grocery retention.",
      "status": "planned",
      "ownerTeamId": "merchant-growth",
      "linkedObjectiveIds": [
        "local-on-demand-delivery-marketplace-2026-q3-multi-vertical"
      ],
      "linkedBrickIds": [
        "whls",
        "catl",
        "cart"
      ],
      "decisionNeededBy": "2026-07-25"
    }
  ]
}
