{"services": ["Aurora PostgreSQL", "SQL Server", "Aurora MySQL", "PostgreSQL", "Any", "MySQL", "Amazon DocumentDB", "Amazon Neptune", "InfluxDB"], "perMonth": [{"month": "2025-03", "total": 19967.198576859897, "services": [{"service": "Aurora PostgreSQL", "usage": 0.6410859696683338, "costs": 12800.6908612064}, {"service": "SQL Server", "usage": 0.27824853007612693, "costs": 5555.8436537494}, {"service": "Aurora MySQL", "usage": 0.03872418772774072, "costs": 773.2135460874}, {"service": "PostgreSQL", "usage": 0.027634956470938075, "costs": 551.7926635181}, {"service": "Any", "usage": 0.005417692428980296, "costs": 108.1761405578}, {"service": "MySQL", "usage": 0.0059741970052445675, "costs": 119.287977941}, {"service": "Amazon DocumentDB", "usage": 0.0025371464679081134, "costs": 50.6597073433}, {"service": "Amazon Neptune", "usage": 0.0003773201547277257, "costs": 7.5340264565}, {"service": "InfluxDB", "usage": 0.0, "costs": 0.0}]}, {"month": "2025-04", "total": 22521.7268191996, "services": [{"service": "Aurora PostgreSQL", "usage": 0.6662903254336737, "costs": 15006.0086916928}, {"service": "SQL Server", "usage": 0.2588288786789914, "costs": 5829.273298528}, {"service": "Aurora MySQL", "usage": 0.040003914758744916, "costs": 900.957239895}, {"service": "PostgreSQL", "usage": 0.023951566809803388, "costs": 539.4306445822}, {"service": "Any", "usage": 0.003639646240963204, "costs": 81.9711183575}, {"service": "MySQL", "usage": 0.004742829793683474, "costs": 106.8167169633}, {"service": "Amazon DocumentDB", "usage": 0.00224451914141886, "costs": 50.5504469435}, {"service": "Amazon Neptune", "usage": 0.00029831914272099205, "costs": 6.7186622373}, {"service": "InfluxDB", "usage": 0.0, "costs": 0.0}]}, {"month": "2025-05", "total": 20476.0796292403, "services": [{"service": "Aurora PostgreSQL", "usage": 0.6199232109674188, "costs": 12693.5970317832}, {"service": "SQL Server", "usage": 0.29738994605108043, "costs": 6089.3802162774}, {"service": "Aurora MySQL", "usage": 0.043846060195821275, "costs": 897.7954199981}, {"service": "PostgreSQL", "usage": 0.026558287708318327, "costs": 543.8096139318}, {"service": "Any", "usage": 0.0034886099945466128, "costs": 71.4330560437}, {"service": "MySQL", "usage": 0.005810556516468005, "costs": 118.9774179214}, {"service": "Amazon DocumentDB", "usage": 0.002615465405483333, "costs": 53.5544779102}, {"service": "Amazon Neptune", "usage": 0.0003678631608632529, "costs": 7.5323953745}, {"service": "InfluxDB", "usage": 0.0, "costs": 0.0}]}, {"month": "2025-06", "total": 18179.709504822604, "services": [{"service": "Aurora PostgreSQL", "usage": 0.6227471839434914, "costs": 11321.362899039}, {"service": "SQL Server", "usage": 0.28430076819836037, "costs": 5168.5053778441}, {"service": "Aurora MySQL", "usage": 0.0488016914877517, "costs": 887.2005745913}, {"service": "PostgreSQL", "usage": 0.030207430883706997, "costs": 549.1623183528}, {"service": "Any", "usage": 0.004277554985307716, "costs": 77.7647070238}, {"service": "MySQL", "usage": 0.006073656854082799, "costs": 110.4173172392}, {"service": "Amazon DocumentDB", "usage": 0.0028840294452720195, "costs": 52.4308175184}, {"service": "Amazon Neptune", "usage": 0.00042050122963032435, "costs": 7.6445902011}, {"service": "InfluxDB", "usage": 0.0002871829723965078, "costs": 5.2209030129}]}, {"month": "2025-07", "total": 19726.621081067, "services": [{"service": "Aurora PostgreSQL", "usage": 0.6674816562877679, "costs": 13167.1577121518}, {"service": "SQL Server", "usage": 0.24208339464540965, "costs": 4775.4873961884}, {"service": "Aurora MySQL", "usage": 0.04800780506237491, "costs": 947.0317793992}, {"service": "PostgreSQL", "usage": 0.028673714852275402, "costs": 565.6355078774}, {"service": "Any", "usage": 0.004050877099129524, "costs": 79.9101175805}, {"service": "MySQL", "usage": 0.005377011331048628, "costs": 106.0702650762}, {"service": "Amazon DocumentDB", "usage": 0.0033604987606886366, "costs": 66.2912856955}, {"service": "Amazon Neptune", "usage": 0.0003840335921173499, "costs": 7.5756851541}, {"service": "InfluxDB", "usage": 0.0005810083691879817, "costs": 11.4613319439}]}, {"month": "2025-08", "total": 17849.557426067902, "services": [{"service": "Aurora PostgreSQL", "usage": 0.6567839516818003, "costs": 11723.3028620641}, {"service": "SQL Server", "usage": 0.22957433840257455, "costs": 4097.8003368683}, {"service": "Aurora MySQL", "usage": 0.05067555552389185, "costs": 904.5362384216}, {"service": "PostgreSQL", "usage": 0.04301726031648999, "costs": 767.8390583313}, {"service": "Any", "usage": 0.004570911059825267, "costs": 81.5887394518}, {"service": "MySQL", "usage": 0.006595998746582711, "costs": 117.7356584094}, {"service": "Amazon DocumentDB", "usage": 0.008781984268835264, "costs": 156.7545325214}, {"service": "Amazon Neptune", "usage": 0.0, "costs": 0.0}, {"service": "InfluxDB", "usage": 0.0, "costs": 0.0}]}, {"month": "2025-09", "total": 17245.540845615797, "services": [{"service": "Aurora PostgreSQL", "usage": 0.6506632238908147, "costs": 11221.0392043491}, {"service": "SQL Server", "usage": 0.23447708689131633, "costs": 4043.6841793452}, {"service": "Aurora MySQL", "usage": 0.049083383027728675, "costs": 846.4694868457}, {"service": "PostgreSQL", "usage": 0.043485052694566394, "costs": 749.9232524179}, {"service": "Any", "usage": 0.004545185241286707, "costs": 78.3841777295}, {"service": "MySQL", "usage": 0.007138095723057295, "costs": 123.1003213519}, {"service": "Amazon DocumentDB", "usage": 0.010607972531230152, "costs": 182.9402235765}, {"service": "Amazon Neptune", "usage": 0.0, "costs": 0.0}, {"service": "InfluxDB", "usage": 0.0, "costs": 0.0}]}, {"month": "2025-10", "total": 18794.728068416607, "services": [{"service": "Aurora PostgreSQL", "usage": 0.6602770313607351, "costs": 12409.7272542464}, {"service": "SQL Server", "usage": 0.2205656399295402, "costs": 4145.471223712}, {"service": "Aurora MySQL", "usage": 0.04657612948339658, "costs": 875.3856881198}, {"service": "PostgreSQL", "usage": 0.03915750040983177, "costs": 735.9545720417}, {"service": "Any", "usage": 0.01811377360514699, "costs": 340.4434492016}, {"service": "MySQL", "usage": 0.006242642020693229, "costs": 117.3287592074}, {"service": "Amazon DocumentDB", "usage": 0.009067283190655766, "costs": 170.4171218877}, {"service": "Amazon Neptune", "usage": 0.0, "costs": 0.0}, {"service": "InfluxDB", "usage": 0.0, "costs": 0.0}]}, {"month": "2025-11", "total": 16503.3524135514, "services": [{"service": "Aurora PostgreSQL", "usage": 0.6137135872822796, "costs": 10128.3316119043}, {"service": "SQL Server", "usage": 0.20260850522205845, "costs": 3343.7195636625}, {"service": "Aurora MySQL", "usage": 0.05561735442531706, "costs": 917.8728003904}, {"service": "PostgreSQL", "usage": 0.04417383006886423, "costs": 729.0162850828}, {"service": "Any", "usage": 0.0673754214442981, "costs": 1111.9203241068}, {"service": "MySQL", "usage": 0.006468873710406723, "costs": 106.7581025616}, {"service": "Amazon DocumentDB", "usage": 0.010042427846775606, "costs": 165.733725843}, {"service": "Amazon Neptune", "usage": 0.0, "costs": 0.0}, {"service": "InfluxDB", "usage": 0.0, "costs": 0.0}]}, {"month": "2025-12", "total": 18486.2408871167, "services": [{"service": "Aurora PostgreSQL", "usage": 0.6252037275385007, "costs": 11557.6667108}, {"service": "SQL Server", "usage": 0.21403789504642962, "costs": 3956.7560867997}, {"service": "Aurora MySQL", "usage": 0.048577593091456456, "costs": 898.017087605}, {"service": "PostgreSQL", "usage": 0.042256932194181716, "costs": 781.1718276922}, {"service": "Any", "usage": 0.05434042400072716, "costs": 1004.5501679855}, {"service": "MySQL", "usage": 0.0065693086024067975, "costs": 121.4418212859}, {"service": "Amazon DocumentDB", "usage": 0.009014119526297616, "costs": 166.6371849484}, {"service": "Amazon Neptune", "usage": 0.0, "costs": 0.0}, {"service": "InfluxDB", "usage": 0.0, "costs": 0.0}]}, {"month": "2026-01", "total": 18017.8784113069, "services": [{"service": "Aurora PostgreSQL", "usage": 0.659467008211398, "costs": 11882.1963702213}, {"service": "SQL Server", "usage": 0.2224499976666165, "costs": 4008.0770105526}, {"service": "Aurora MySQL", "usage": 0.045952402214315125, "costs": 827.964795805}, {"service": "PostgreSQL", "usage": 0.04603852363999454, "costs": 829.5165211815}, {"service": "Any", "usage": 0.013632258491058603, "costs": 245.6243759634}, {"service": "MySQL", "usage": 0.006693356070003163, "costs": 120.6000758329}, {"service": "Amazon DocumentDB", "usage": 0.005766453706613941, "costs": 103.8992617502}, {"service": "Amazon Neptune", "usage": 0.0, "costs": 0.0}, {"service": "InfluxDB", "usage": 0.0, "costs": 0.0}]}, {"month": "2026-02", "total": 15297.9225554499, "services": [{"service": "Aurora PostgreSQL", "usage": 0.6470904150679937, "costs": 9899.1390560841}, {"service": "SQL Server", "usage": 0.22581684517386452, "costs": 3454.5286091858}, {"service": "Aurora MySQL", "usage": 0.052638283956453064, "costs": 805.2563914176}, {"service": "PostgreSQL", "usage": 0.05860642119206577, "costs": 896.5564926483}, {"service": "Any", "usage": 0.006227963903135215, "costs": 95.2749094683}, {"service": "MySQL", "usage": 0.006908770700080965, "costs": 105.6898391232}, {"service": "Amazon DocumentDB", "usage": 0.0027113000064066663, "costs": 41.4772575226}, {"service": "Amazon Neptune", "usage": 0.0, "costs": 0.0}, {"service": "InfluxDB", "usage": 0.0, "costs": 0.0}]}]}