{
  "portfolio": {
    "name": "Mental Wellbeing Community Platform Portfolio",
    "version": "1.0",
    "products": [
      {
        "id": "p1",
        "name": "Member App and Community Experience",
        "type": "B2C",
        "primaryCustomers": [
          {
            "id": "cg1-p1",
            "name": "Everyday Member"
          }
        ],
        "interfaces": [
          {
            "type": "web",
            "name": "Cadre Web App",
            "description": "Browser experience for support discovery, community, live sessions, and progress.",
            "users": [
              "Members"
            ],
            "availabilityHorizon": "live"
          },
          {
            "type": "mobile_app",
            "name": "Cadre iOS App",
            "description": "Native iOS member experience for always-on support access.",
            "users": [
              "Members"
            ],
            "availabilityHorizon": "live"
          },
          {
            "type": "mobile_app",
            "name": "Cadre Android App",
            "description": "Native Android member experience for community and live support.",
            "users": [
              "Members"
            ],
            "availabilityHorizon": "live"
          }
        ],
        "deploymentModelRef": "deployment.json",
        "neededBricks": [
          {
            "whyNeeded": "Turns member intent into the right support option quickly.",
            "mappingType": "inferred_from_product_definition",
            "brickId": "home",
            "brickName": "Member Home and Intent Feed"
          },
          {
            "whyNeeded": "Helps members navigate topics and explicit search paths.",
            "mappingType": "inferred_from_product_definition",
            "brickId": "topics",
            "brickName": "Topic and Pathway Taxonomy"
          },
          {
            "whyNeeded": "Supports social participation and shared support.",
            "mappingType": "inferred_from_product_definition",
            "brickId": "community",
            "brickName": "Community Feed"
          },
          {
            "whyNeeded": "Provides immediate access to live support sessions.",
            "mappingType": "inferred_from_product_definition",
            "brickId": "live",
            "brickName": "Live Session Streaming"
          },
          {
            "whyNeeded": "Sustains repeat use through reminders and progress.",
            "mappingType": "inferred_from_product_definition",
            "brickId": "progress",
            "brickName": "Progress and Reflection Tracking"
          }
        ]
      },
      {
        "id": "p2",
        "name": "Employer Wellness Program Console",
        "type": "B2B2C",
        "primaryCustomers": [
          {
            "id": "cg2-p1",
            "name": "People and Benefits Leader"
          },
          {
            "id": "cg3-p1",
            "name": "HR Program Administrator"
          }
        ],
        "interfaces": [
          {
            "type": "web",
            "name": "Employer Admin Console",
            "description": "Browser experience for onboarding, program reviews, account health, and live event planning.",
            "users": [
              "People leaders",
              "Benefits admins"
            ],
            "availabilityHorizon": "live"
          }
        ],
        "deploymentModelRef": "deployment.json",
        "neededBricks": [
          {
            "whyNeeded": "Packages commercial terms and seat logic for employer plans.",
            "mappingType": "inferred_from_product_definition",
            "brickId": "team-plan",
            "brickName": "Team Plan Packaging and Contracting"
          },
          {
            "whyNeeded": "Launches employers and configures workforce access.",
            "mappingType": "inferred_from_product_definition",
            "brickId": "org-onboarding",
            "brickName": "Organization Onboarding and Access Codes"
          },
          {
            "whyNeeded": "Provides the operational control plane for employer programs.",
            "mappingType": "inferred_from_product_definition",
            "brickId": "admin-console",
            "brickName": "Employer Admin Console"
          },
          {
            "whyNeeded": "Shows employer-safe engagement and renewal signals.",
            "mappingType": "inferred_from_product_definition",
            "brickId": "engagement-analytics",
            "brickName": "Employer Engagement Analytics"
          },
          {
            "whyNeeded": "Supports custom employer programming and live events.",
            "mappingType": "inferred_from_product_definition",
            "brickId": "events",
            "brickName": "Employer Live Events Program"
          }
        ]
      },
      {
        "id": "p3",
        "name": "Contributor Studio and Live Delivery",
        "type": "B2B2C",
        "primaryCustomers": [
          {
            "id": "cg4-p1",
            "name": "Contributor / Facilitator"
          }
        ],
        "interfaces": [
          {
            "type": "web",
            "name": "Contributor Studio",
            "description": "Browser experience for profile management, publishing, scheduling, and earnings.",
            "users": [
              "Contributors",
              "Facilitators",
              "Experts"
            ],
            "availabilityHorizon": "live"
          }
        ],
        "deploymentModelRef": "deployment.json",
        "neededBricks": [
          {
            "whyNeeded": "Establishes trusted contributor identity and topic fit.",
            "mappingType": "inferred_from_product_definition",
            "brickId": "contributor-profile",
            "brickName": "Contributor Profiles and Credentials"
          },
          {
            "whyNeeded": "Supports content publishing and reuse.",
            "mappingType": "inferred_from_product_definition",
            "brickId": "content-studio",
            "brickName": "Content Studio and Publishing"
          },
          {
            "whyNeeded": "Coordinates contributor availability and sessions.",
            "mappingType": "inferred_from_product_definition",
            "brickId": "session-scheduling",
            "brickName": "Session Scheduling and Availability"
          },
          {
            "whyNeeded": "Runs safe live session delivery.",
            "mappingType": "inferred_from_product_definition",
            "brickId": "live",
            "brickName": "Live Session Streaming"
          },
          {
            "whyNeeded": "Makes contributor compensation legible and reliable.",
            "mappingType": "inferred_from_product_definition",
            "brickId": "payouts",
            "brickName": "Contributor Payouts and Earnings"
          }
        ]
      }
    ]
  }
}
